uoload lab4.zip/lab4_DigiHockey.v
/*module up_down_counter_x(
    input clk,
    input reset,
    output [2:0] counter

);

reg [2:0] counter_up_down;
reg increment;  // New variable to determine direction

// down counter
always @(posedge clk or posedge reset) begin
    if (reset) begin
        counter_up_down <= 3'h0;
        increment <= 1'b1;  // Initialize to increment
    end else begin
        if (counter_up_down < 3'h4) begin
            if (increment)
                counter_up_down <= counter_up_down + 3'd1;
            else
                counter_up_down <= counter_up_down - 3'd1;
        end
        // Change direction when reaching 4 or 0
        if (counter_up_down == 3'h4 || counter_up_down == 3'h0)
            increment <= ~increment;
    end 
end

assign counter = counter_up_down;

endmodule

module up_down_counter_y(
    input clk,
    input [2:0] INIT_Y_POS,
    input reset,
    input [1:0] DIRECTION,
    output  [2:0] counter
);

reg [3:0] counter_up_down;
reg increment;

// down counter
always @(posedge clk or posedge reset) begin
    counter_up_down = INIT_Y_POS;
    if (reset) begin
        counter_up_down <= 3'h0;
        if (DIRECTION == 2'b01)
            increment <= 1'b1;  // Initialize to increment
        else if (DIRECTION == 2'b10)
            increment <= 1'b0;  // Initialize to decrement
    end
    if (DIRECTION != 2'b00) begin
        if (counter_up_down < 3'h4) begin
            if (increment)
                counter_up_down <= counter_up_down + 3'd1;
            else
                counter_up_down <= counter_up_down - 3'd1;
        end
        // Change direction when reaching 4 or 0
        if (counter_up_down == 3'h4 || counter_up_down == 3'h0)
            increment <= ~increment;
    end
end

assign counter = counter_up_down;

endmodule
module DigiHockey(
    input clk,
    input rst,
    input START,
    input [1:0] DIRECTION,
    input [2:0] INIT_Y_POS,
    output [2:0] X_COORD,
    output [2:0] Y_COORD
);
reg [2:0]X_c;
reg [2:0]Y_c;
req started;
reg increment_x;
reg increment_y;

always @(posedge clk or posedge rst) begin
    if (rst) begin
        // Reset logic here
        X_c <= 3'h0;
        Y_c <= 3'h0;
        increment_x <= 1'b1;
        started <= 0;
    end else if (START) begin
        // Initialize counters when START is asserted
        X_c <= 3'h0;
        Y_c <= INIT_Y_POS;
        started <= 1;
    end else if (started) begin 
            if (X_c < 3'h4) begin
                if (increment_x)begin
                    X_c <= X_c + 3'd1;
                else
                    x_c <= X_c - 3'd1;
            end
            // Change direction when reaching 4 or 0
            if (X_c == 3'h4 || X_c == 3'h0)
                increment_x <= ~increment_X;
    end 
    if (DIRECTION == 2'b01) 
        increment_y <= 1'b1;  // Initialize to increment
    else if (DIRECTION == 2'b10)
        increment_y <= 1'b0;  // Initialize to decrement

    if (DIRECTION != 2'b00 && Y_c < 3'h4) begin
            if (increment_y)
                Y_c <= Y_c + 3'd1;
            else
                Y_c <= Y_c - 3'd1;
        end
        // Change direction when reaching 4 or 0
        if (Y_c == 3'h4 || Y_c == 3'h0)
            increment_y <= ~increment_y;
        
    end

        

assign X_COORD = X_c;
assign Y_COORD = Y_c;

endmodule

module DigiHockey(
    input clk,
    input rst,
    input START,
    input [1:0] DIRECTION,
    input [2:0] INIT_Y_POS,
    output reg [2:0] X_COORD,
    output reg [2:0] Y_COORD
);

    reg started;
    reg increment_x;
    reg increment_y;

    always @(posedge clk or posedge rst) begin
        if (rst) begin
            // Reset logic here
            X_COORD <= 3'h0;
            Y_COORD <= 3'h0;
            increment_x <= 1'b1;
            started <= 0;
        end else if (START && started!=1) begin
            // Initialize counters when START is asserted
            X_COORD <= 3'h0;
            Y_COORD <= INIT_Y_POS;
            started <= 1;
        end if (started) begin 
            if (X_COORD <= 3'h3 && X_COORD >= 3'h1) begin
                if (increment_x)
                    X_COORD <= X_COORD + 3'b001;
                else
                    X_COORD <= X_COORD - 3'b001;
    
                if (X_COORD == 3'h3 || X_COORD == 3'h1)
                    increment_x <= ~increment_x;
            end
            
        end

        if (DIRECTION == 2'b01) 
            increment_y <= 1'b1;  // Initialize to increment
        else if (DIRECTION == 2'b10)
            increment_y <= 1'b0;  // Initialize to decrement

        if (DIRECTION != 2'b00 && Y_COORD < 3'h4) begin
            if (increment_y)
                Y_COORD <= Y_COORD + 3'd1;
            else
                Y_COORD <= Y_COORD - 3'd1;
        end
        // Change direction when reaching 4 or 0
        if (Y_COORD == 3'h4 || Y_COORD == 3'h0)
            increment_y <= ~increment_y;
    end
    // Continuous assignments for X_COORD and Y_COORD

endmodule

module DigiHockey(
    input clk,
    input rst,
    input START,
    input [1:0] DIRECTION,
    input [2:0] INIT_Y_POS,
    output reg [2:0] X_COORD,
    output reg [2:0] Y_COORD
);

    reg started;
    reg increment_x;
    reg increment_y;

    always @(posedge clk or posedge rst) begin
        if (rst) begin
            // Reset logic here
            X_COORD <= 3'h0;
            Y_COORD <= 3'h0;
            increment_x <= 1'b1;
            started <= 0;end
        else if (!started && START) begin  // Fixed condition
            // Initialize counters when START is asserted
            X_COORD <= 3'h0;
            Y_COORD <= INIT_Y_POS;
            started <= 1;
        end

        if (started) begin 
            if (X_COORD == 3'h1) // Adjusted condition
                increment_x <= 1;

            if (increment_x)
                X_COORD <= X_COORD + 3'b001;

            else
                X_COORD <= X_COORD - 3'b001;

            if(X_COORD == 3'h3)
                increment_x<=0;
            
        end

        if (DIRECTION == 2'b01) begin
            increment_y <= 1'b1;end

        
        
        // Additional conditions to control increment_y
        

        else if (Y_COORD == 3'h0) begin 
            increment_y <= 1'b1;
        end 
        
        if (DIRECTION != 2'b00) begin
            if (increment_y)
                Y_COORD <= Y_COORD + 3'd1;
            else
                Y_COORD <= Y_COORD - 3'd1;
        end
        if (Y_COORD == 3'h4) begin
            increment_y <= 0;  // Set increment_y to 0 when reaching 3'h4
        end 
    else if (DIRECTION == 2'b10) begin
        increment_y <= 1'b0;
    end
        
    end        
    // Continuous assignments for X_COORD and Y_COORD

endmodule
*/
module DigiHockey(
    input clk,
    input rst,
    input START,
    input [1:0] DIRECTION,
    input [2:0] INIT_Y_POS,
    output reg [2:0] X_COORD,
    output reg [2:0] Y_COORD
);

    reg started;
    reg increment_x;
    reg increment_y;
    reg y_set;

    always @(posedge clk or posedge rst) begin
        if (rst) begin
            // Reset logic here
            X_COORD <= 3'h0;
            Y_COORD <= 3'h0;
            increment_x <= 1'b1;
            started <= 0;
        end
        else if (!started && START) begin  // Fixed condition
            // Initialize counters when START is asserted
            X_COORD <= 3'h0;
            Y_COORD <= 3'h0;
            started <= 1;
            increment_y <= DIRECTION;
            y_set<=0;
        end
        else if(!y_set)begin 
            Y_COORD <= INIT_Y_POS;
            y_set<=1;
        end

        if (started&&y_set) begin 
            
            if (X_COORD == 3'h1) // Adjusted condition
                increment_x <= 1;

            if (increment_x)
                X_COORD <= X_COORD + 3'b001;

            else
                X_COORD <= X_COORD - 3'b001;

            if(X_COORD == 3'h3)
                increment_x<=0;
            
            if(increment_y == DIRECTION)begin
                if (DIRECTION == 2'b10) begin
                    increment_y <= 2'b10;
                end
                if (DIRECTION == 2'b01)begin 
                    increment_y<= 2'b01;
                end
                if (Y_COORD == 3'h1) begin 
                    increment_y <= 2'b01;
                end 
                if (Y_COORD == 3'h3) begin
                    increment_y <= 2'b10;  // Set increment_y to 0 when reaching 3'h4
                end 
            end
            if(increment_y != DIRECTION)begin
                if (Y_COORD == 3'h1) begin 
                    increment_y <= 2'b01;
                end 
                if (Y_COORD == 3'h3) begin
                    increment_y <= 2'b10;  // Set increment_y to 0 when reaching 3'h4
                end 
            end
            if (DIRECTION != 2'b00) begin
                if (increment_y==2'b01)
                    Y_COORD <= Y_COORD + 3'd1;
                else
                    Y_COORD <= Y_COORD - 3'd1;
            end
       
                
            
        end
    end
    // Continuous assignments for X_COORD and Y_COORD

endmodule

uoload lab4.zip/lab4_DigiHockey_tb.v
module DigiHockey_tb();


// Do not worry too much about these parameter statements, they are here to ease your work
parameter HP = 5;       // Half period of our clock signal
parameter FP = (2*HP);  // Full period of our clock signal

reg clk, rst, START;
reg [1:0] DIRECTION;
reg [2:0] INIT_Y_POS;

wire [2:0] X_COORD, Y_COORD;

// Our design-under-test is the DigiHockey module
DigiHockey dut(clk, rst, START, DIRECTION, INIT_Y_POS, X_COORD, Y_COORD);

// This always statement automatically cycles between clock high and clock low in HP (Half Period) time. Makes writing test-benches easier.
always #HP clk = ~clk;

initial begin
    $dumpfile("DigiHockey.vcd"); //  * Our waveform is saved under this file.
    $dumpvars(0,DigiHockey_tb); // * Get the variables from the module.
    
    $display("Simulation started.");

    // * Initialize the testbench variables
    clk = 0; // Set clock low (we won't have to write clk = 1 again, thanks to those parameter and always statements we gave you)
    rst = 0;
    START = 0;
    DIRECTION = 0;
    INIT_Y_POS = 0;
    #10
   

    clk = 0;
    rst = 1;
    START = 0;
    DIRECTION = 2'b01;
    INIT_Y_POS = 3'h2;
  
   

    // Apply reset
    #10 rst = 0;

    // Apply START signal
    #10 START = 1;
    #60

    clk = 0;
    rst = 1;
    START = 0;
    DIRECTION = 2'b10;
    INIT_Y_POS = 3'h4;

   

    // Apply reset
    #10 rst = 0;

    // Apply START signal
    #10 START = 1;
    #80
    clk = 0;
    rst = 1;
    START = 0;
    DIRECTION = 2'b00;
    INIT_Y_POS = 3'h0;

     // Apply reset
    #10 rst = 0;

    // Apply START signal
    #10 START = 1;
    #150;
    $finish;


	
	// Here, you are asked to write your test scenario.
	// The test scenario must cover all possible cases (moving directions and bouncings)
	
	
	
	
    $display("Simulation finished.");
    $finish(); // Finish simulation.
end



endmodule

uoload lab4.zip/DigiHockey.vcd
$date
	Tue Dec 19 22:45:33 2023
$end
$version
	Icarus Verilog
$end
$timescale
	1s
$end
$scope module DigiHockey_tb $end
$var wire 3 ! Y_COORD [2:0] $end
$var wire 3 " X_COORD [2:0] $end
$var parameter 64 # FP $end
$var parameter 32 $ HP $end
$var reg 2 % DIRECTION [1:0] $end
$var reg 3 & INIT_Y_POS [2:0] $end
$var reg 1 ' START $end
$var reg 1 ( clk $end
$var reg 1 ) rst $end
$scope module dut $end
$var wire 2 * DIRECTION [1:0] $end
$var wire 3 + INIT_Y_POS [2:0] $end
$var wire 1 ' START $end
$var wire 1 ( clk $end
$var wire 1 ) rst $end
$var reg 3 , X_COORD [2:0] $end
$var reg 3 - Y_COORD [2:0] $end
$var reg 1 . increment_x $end
$var reg 1 / increment_y $end
$var reg 1 0 started $end
$var reg 1 1 y_set $end
$upscope $end
$upscope $end
$enddefinitions $end
$comment Show the parameter values. $end
$dumpall
b101 $
b1010 #
$end
#0
$dumpvars
x1
x0
x/
x.
bx -
bx ,
b0 +
b0 *
0)
0(
0'
b0 &
b0 %
bx "
bx !
$end
#5
1(
#10
00
1.
b0 !
b0 -
b0 "
b0 ,
b10 &
b10 +
b1 %
b1 *
1)
1(
#15
0(
#20
1(
0)
#25
0(
#30
01
1/
10
1(
1'
#35
0(
#40
11
b10 !
b10 -
1(
#45
0(
#50
b11 !
b11 -
b1 "
b1 ,
1(
#55
0(
#60
b100 !
b100 -
0/
b10 "
b10 ,
1(
#65
0(
#70
b11 !
b11 -
b11 "
b11 ,
1(
#75
0(
#80
b10 !
b10 -
0.
b100 "
b100 ,
1(
#85
0(
#90
00
1.
b1 !
b1 -
b11 "
b11 ,
1(
b100 &
b100 +
b10 %
b10 *
0'
1)
#95
0(
#100
1(
0)
#105
0(
#110
01
10
b0 !
b0 -
b0 "
b0 ,
1(
1'
#115
0(
#120
11
b100 !
b100 -
1(
#125
0(
#130
b11 !
b11 -
b1 "
b1 ,
1(
#135
0(
#140
b10 !
b10 -
b10 "
b10 ,
1(
#145
0(
#150
b1 !
b1 -
b11 "
b11 ,
1(
#155
0(
#160
b0 !
b0 -
1/
0.
b100 "
b100 ,
1(
#165
0(
#170
b1 !
b1 -
b11 "
b11 ,
1(
#175
0(
#180
b10 !
b10 -
b10 "
b10 ,
1(
#185
0(
#190
00
1.
b0 !
b0 -
b1 "
b1 ,
1(
b0 &
b0 +
b0 %
b0 *
0'
1)
#195
0(
#200
1(
0)
#205
0(
#210
01
0/
10
b0 "
b0 ,
1(
1'
#215
0(
#220
11
1(
#225
0(
#230
b1 "
b1 ,
1(
#235
0(
#240
b10 "
b10 ,
1(
#245
0(
#250
b11 "
b11 ,
1(
#255
0(
#260
0.
b100 "
b100 ,
1(
#265
0(
#270
b11 "
b11 ,
1(
#275
0(
#280
b10 "
b10 ,
1(
#285
0(
#290
b1 "
b1 ,
1(
#295
0(
#300
b0 "
b0 ,
1.
1(
#305
0(
#310
b1 "
b1 ,
1(
#315
0(
#320
b10 "
b10 ,
1(
#325
0(
#330
b11 "
b11 ,
1(
#335
0(
#340
0.
b100 "
b100 ,
1(
#345
0(
#350
b11 "
b11 ,
1(
#355
0(
#360
b10 "
b10 ,
1(
