hockey.v

`include "debouncer.v" 
module hockey(

    input clk,
    input rst,
    
    input BTN_A,
    input BTN_B,
    
    input [1:0] DIR_A,
    input [1:0] DIR_B,
    
    input [2:0] Y_in_A,
    input [2:0] Y_in_B,
   
    
    output reg [6:0] SSD7,
    output reg [6:0] SSD6,
    output reg [6:0] SSD5,
    output reg [6:0] SSD4, 
    output reg [6:0] SSD3,
    output reg [6:0] SSD2,
    output reg [6:0] SSD1,
    output reg [6:0] SSD0, 
    
	output reg [2:0] X_COORD,
	output reg [2:0] Y_COORD,

    output reg LD0,
    output reg LD5,
    output reg LD6,
    output reg LD7,
    output reg LD8,
    output reg LD9,
    output reg LD15
  
  

    );


    

    parameter [3:0] IDLE = 0;
    parameter [3:0] DISP = 1;
    parameter [3:0] HIT_A = 2;
    parameter [3:0] HIT_B = 3;
    parameter [3:0] SEND_A = 4;
    parameter [3:0] SEND_B = 5; 
    parameter [3:0] RESP_A = 6;
    parameter [3:0] RESP_B = 7;
    parameter [3:0] GOAL_A = 8;
    parameter [3:0] GOAL_B = 9;
    parameter [3:0] END_state = 10;


    
    reg Turn;
    reg [1:0] Timer;
    reg [1:0] direction_Y;
    reg [1:0] Score_A;
    reg [1:0] Score_B;


    reg [3:0] State; 

    
    
    
    
    


    always @(posedge clk or posedge rst) //comb. part for state transitions
    begin

        if(rst) begin
            State <= IDLE;
            
            Timer <= 0;
            
            
            Score_A <= 0;
            Score_B <= 0;
            X_COORD <= 0;
            Y_COORD <= 0;
            SSD2 <= 7'b0000000; // Turn off SSD
            SSD0 <= 7'b0000000;
            SSD7 <= 7'b0000000;
            SSD6 <= 7'b0000000;
            LD0 <=0;
            LD5 <=0;
            LD6 <=0;
            LD7 <=0;
            LD8 <=0;
            LD9 <=0;
            LD15 <=0;
            

            
        end



        else begin
            
        
        case(State)
        IDLE:
        begin

        if(BTN_A  == 1)
        begin
            Turn<= 0;
            State <= DISP; 
        end

        else if(BTN_B == 1)begin
            Turn<= 1;  
            State <= DISP; 
        end

        else begin
            State <=IDLE ;
        end
        end


        DISP://show initial score for 2 seconds 
        begin
            SSD2<=Score_A;//display scores
            SSD1 <= 7'b1111110;
            SSD0<=Score_B;
            if(Timer < 2) begin
                
                Timer <= Timer + 1;
                State <= DISP;

            end

            else begin
                Timer <= 0 ;

                if(Turn == 1)begin
                    State <= HIT_B; 
                end

                else begin
                    State <= HIT_A; 
                end

            end

        end


        HIT_B: begin
            LD9<=0;
            LD8<=0;
            LD7<=0;
            LD6<=0;
            LD5<=0;
            LD0<=1;//expecting hit from B
            SSD2 <= 7'b0000000; // Turn off SSD
            SSD0 <= 7'b0000000;
            SSD1 <= 7'b0000000;

        if(BTN_B == 1 && (Y_in_B <5)) begin
            X_COORD <= 4;
            Y_COORD <= Y_in_B;
            direction_Y <= DIR_B;
            State <= SEND_A; 
            
        end

        else begin
            State <= HIT_B; 
        end
        end

        HIT_A: begin
            LD9 <= 0;
            LD8 <= 0;
            LD7 <= 0;
            LD6 <= 0;
            LD5 <= 0;
            LD15 <=1; //expecting Hit from A
            SSD2 <= 7'b0000000; // Turn off SSD
            SSD0 <= 7'b0000000;
            SSD1 <= 7'b0000000;

        if(BTN_A == 1 && (Y_in_A < 5)) begin
            X_COORD <= 0;
            Y_COORD <= Y_in_A;
            direction_Y <= DIR_A;
            State <= SEND_B; 

        end

        else begin
            State <= HIT_A; 
        end
        end

        SEND_A:  begin
            LD0<=0;
            //ld logic
            if(X_COORD==4)begin LD9<=1;SSD4<=4; end
            else if(X_COORD==3)begin LD9<=0; LD8<=1;SSD4<=3; end
            else if(X_COORD==2)begin LD8<=0; LD7<=1;SSD4<=2; end
            else if(X_COORD==1)begin LD7<=0; LD6<=1;SSD4<=1; end
            else if(X_COORD==0)begin LD6<=0; LD5<=1;SSD4<=0; end
          
            SSD5<=Y_COORD;
            if(Timer < 2)begin
                Timer <= Timer + 1;
                State<=SEND_A;
            end

            else begin
               Timer <= 0;

               if(direction_Y == 0) begin // straight direction
                if(X_COORD > 1)begin
                    X_COORD <= X_COORD -1;
                    SSD4<=SSD4-1;
                    State <= SEND_A;
                end

                else begin
                    X_COORD <= 0;
                    SSD4<=SSD4-1;
                    State <= RESP_A; 
                end
               end


               if(direction_Y == 2'b01)begin // up direction
                 if(Y_COORD == 4)begin
                    direction_Y <= 2'b10;
                    Y_COORD <= Y_COORD - 1;  
                    SSD5<=SSD5-1;  
                    if(X_COORD > 1)begin
                        X_COORD <= X_COORD -1;
                        SSD4<=SSD4-1;
                        State <= SEND_A;  
                    end
                    else begin
                        X_COORD <= 0;
                        SSD4<=SSD4-1;
                        State <= RESP_A; 
                    end
                end

                else begin
                    Y_COORD <= Y_COORD + 1;
                    SSD5<=SSD5+1;
                    if(X_COORD > 1)begin
                        X_COORD <= X_COORD -1;
                        SSD4<=SSD4-1;
                        State <= SEND_A  ;    
                    end
                    else begin
                        X_COORD <= 0;
                        SSD4<=SSD4-1;
                        State <= RESP_A; 
                    end
                end
               end

               if(direction_Y == 2'b10)begin //down direction
                   if(Y_COORD == 0)begin
                    direction_Y <= 2'b01;
                    Y_COORD <= Y_COORD + 1;
                    SSD5<=SSD5+1; 

                    if(X_COORD > 1)begin
                        X_COORD <= X_COORD -1;
                        SSD4<=SSD4-1;
                        State <= SEND_A   ;   
                    end
                    else begin
                        X_COORD <= 0;
                        SSD4<=SSD4-1;
                        State <= RESP_A; 
                    end

                   end

                   else begin
                    Y_COORD <= Y_COORD - 1;
                    SSD5<=SSD5-1; 

                    if(X_COORD > 1)begin
                        X_COORD <= X_COORD -1;
                        SSD4<=SSD4-1;
                        State <= SEND_A  ;    
                    end
                    else begin
                        X_COORD <= 0;
                        SSD4<=SSD4-1;
                        State <= RESP_A; 
                    end
                   end



                end

            end

        end
      
        SEND_B: begin
            LD15<=0;
            if(X_COORD==0)begin LD5<=1;SSD4<=0; end
            else if(X_COORD==1)begin LD5<=0; LD6<=1;SSD4<=1; end
            else if(X_COORD==2)begin LD6<=0; LD7<=1;SSD4<=2; end
            else if(X_COORD==3)begin LD7<=0; LD8<=1;SSD4<=3; end
            else if(X_COORD==4)begin LD8<=0; LD9<=1;SSD4<=4; end
            if(Y_COORD==5)begin SSD5<=5; end
            else if(Y_COORD==4)begin  SSD5<=4; end
            else if(Y_COORD==3)begin  SSD5<=3; end
            else if(Y_COORD==2)begin  SSD5<=2; end
            else if(Y_COORD==1)begin  SSD5<=1; end
            if(Timer < 2) begin
                Timer <= Timer + 1;
                State <= SEND_B;
            end
            else begin
                Timer <= 0;

                if(direction_Y == 2'b00) begin // straight
                    if(X_COORD < 3)begin
                        X_COORD <= X_COORD + 1;
                        SSD4 <= SSD4 +1;
                        State <= SEND_B;
                    end

                    else begin
                        X_COORD <= 4;
                        SSD4<=SSD4+1;
                        State <= RESP_B;
                    end
                end

                else if(direction_Y == 2'b01)begin//up
                    if(Y_COORD == 4)begin
                        direction_Y <= 2'b10;
                        Y_COORD <= Y_COORD - 1;
                        SSD5<=SSD5-1;
                         
                        if(X_COORD < 3)begin
                            X_COORD <= X_COORD + 1;
                            SSD4<= SSD4+1;
                            State <= SEND_B;
                        end
    
                        else begin
                            X_COORD <= 4;
                            SSD4<=SSD4+1;
                            State <= RESP_B;
                        end


                    end

                    else begin
                        Y_COORD <= Y_COORD + 1;
                        SSD5<=SSD5+1;

                        if(X_COORD < 3)begin
                            X_COORD <= X_COORD + 1;
                            SSD4<=SSD4+1;
                            State <= SEND_B;
                        end
    
                        else begin
                            X_COORD <= 4;
                            SSD4<=SSD4+1;
                            State <= RESP_B;
                        end
                    end
                    
                end


                else if(direction_Y == 2'b10) begin//down
                        if(Y_COORD == 0)begin

                            direction_Y <= 2'b01;
                            Y_COORD <= Y_COORD + 1;
                            SSD5<=SSD5+1;

                            if(X_COORD < 3)begin
                                X_COORD <= X_COORD + 1;
                                SSD4<=SSD4+1;
                                State <= SEND_B;
                            end
        
                            else begin
                                X_COORD <= 4;
                                SSD4<=SSD4+1;
                                State <= RESP_B;
                            end
                        end

                        else begin
                            Y_COORD <= Y_COORD - 1;
                            SSD5<=SSD5-1;

                            if(X_COORD < 3)begin
                                X_COORD <= X_COORD + 1;
                                SSD4<=SSD4+1;
                                State <= SEND_B;
                            end
        
                            else begin
                                X_COORD <= 4;
                                SSD4<=SSD4+1;
                                State <= RESP_B;
                            end
                         end
                end

            end
        end


    RESP_A: begin
     LD5<=0;
     if(Timer < 2)begin

        if(BTN_A == 1 && (Y_COORD == Y_in_A))begin
          X_COORD <= 1;
          Timer <= 0;
        
          if(DIR_A == 2'b00) begin
            direction_Y <= DIR_A;
            State <= SEND_B;
            end

          else if(DIR_A == 2'b01) begin

            if(Y_COORD == 4)begin
                direction_Y <= 2'b10;
                Y_COORD <= Y_COORD -1;
                State <= SEND_B;
            end

            else begin
                direction_Y <= DIR_A;
                Y_COORD <= Y_COORD +1;
                State <= SEND_B;

            end
            
          end


          else if(DIR_A == 2'b10)begin
            
            if(Y_COORD == 0)begin
                direction_Y <= 2'b01;
                Y_COORD <= Y_COORD + 1;
                State <= SEND_B;

            end

            else begin
                direction_Y <= DIR_A;
                Y_COORD <= Y_COORD - 1;
                State <= SEND_B;
            end



          end


        end

        else begin
            Timer <=Timer + 1;
            State <= RESP_A;
    
    
         end
        
     end

     else begin
        Timer <= 0;
        Score_B <= Score_B + 1;
       

        State <= GOAL_B;

     end

    end




    RESP_B: begin
    LD9<=0;
    if(Timer < 2)begin
       if(BTN_B== 1 && (Y_COORD == Y_in_B))begin
        X_COORD <= 3;
        Timer <= 0;

        if(DIR_B == 2'b00)begin
            direction_Y <= DIR_B;
            State <= SEND_A;
        end

        else if(DIR_B == 2'b01) begin
            if(Y_COORD == 4)begin
                direction_Y <= 2'b10;
                Y_COORD <= Y_COORD -1;
                State <= SEND_A;
            end

            else begin
                direction_Y <= DIR_B   ;
                Y_COORD <= Y_COORD + 1;
                State <= SEND_A;
            end
        end

        else if(DIR_B == 2'b10) begin

            if(Y_COORD == 0)begin
                direction_Y <= 2'b01;
                Y_COORD <= Y_COORD +1;
                State <= SEND_A;
            end

            else begin
                direction_Y <= DIR_B;
                Y_COORD <= Y_COORD -1;
                State <= SEND_A;
            end
            
        end


       end

       else begin
        Timer <= Timer + 1;
        State <= RESP_B;
       end
    end


    else begin
        Timer <= 0;
        Score_A <= Score_A + 1;
        State <= GOAL_A; 
    end

    end

    
   
  
    GOAL_B: begin
        LD9<=1;
        LD8<=1;
        LD7<=1;
        LD6<=1;
        LD5<=1;
        SSD0<=Score_B;
        SSD2<=Score_A;
        if(Timer < 2) begin
            Timer <= Timer + 1;
            State <= GOAL_B; 
        end
        else begin
            Timer <= 0;

            if(Score_B == 3) begin
                Turn <= 1; 
                State <= END_state; 
            end

            else begin
                State <= HIT_A; 
            end
        end


    end

    GOAL_A: begin
        LD9<=1;
        LD8<=1;
        LD7<=1;
        LD6<=1;
        LD5<=1;
        SSD2<=Score_A;
        SSD0<=Score_B;
        if(Timer < 2)begin
            Timer <= Timer + 1;
            State <= GOAL_A; 
        end
        else begin
            Timer <= 0;

            if(Score_A == 3)begin
                Turn <= 0;
                State <= END_state; 
            end

            else begin
                State <= HIT_B; 
            end
        end




    end
    

    END_state: begin
        SSD0<=Score_B;
        SSD2<=Score_A;
        if(Score_A==2'b10)begin SSD5<= 7'b1100000; end
        else if(Score_B==2'b10)begin SSD5<= 7'b0001000; end
        if (Timer % 4 == 0) begin
            LD9 <= ~LD9; // Toggle LD9
            LD8 <= ~LD8; // Toggle LD8
            LD7 <= ~LD7; // Toggle LD7
            LD6 <= ~LD6; // Toggle LD6
            LD5 <= ~LD5; // Toggle LD5
        end
        
    
        // Increment Timer
        Timer <= Timer + 1;    
        State <= END_state; 
    end





endcase

end

end




    
    
endmodule

hockey_tb_phase2.v
module hockey_tb();


parameter HP = 5;       // Half period of our clock signal
parameter FP = (2*HP);  // Full period of our clock signal

reg clk, rst, BTN_A, BTN_B;
reg [1:0] DIR_A;
reg [1:0] DIR_B;
reg [2:0] Y_in_A;
reg [2:0] Y_in_B;

wire [2:0] X_COORD, Y_COORD;
wire [6:0] SSD5, SSD4, SSD2, SSD0;
wire LD0, LD5, LD6, LD7, LD8, LD9, LD15;

// Our design-under-test is the DigiHockey module
hockey dut(
    .clk(clk),
    .rst(rst),
    .BTN_A(BTN_A),
    .BTN_B(BTN_B),
    .DIR_A(DIR_A),
    .DIR_B(DIR_B),
    .Y_in_A(Y_in_A),
    .Y_in_B(Y_in_B),
    .SSD5(SSD5),
    .SSD4(SSD4),
    .SSD2(SSD2),
    .SSD0(SSD0),
    .X_COORD(X_COORD),
    .Y_COORD(Y_COORD),
    .LD0(LD0),
    .LD5(LD5),
    .LD6(LD6),
    .LD7(LD7),
    .LD8(LD8),
    .LD9(LD9),
    .LD15(LD15)
);

// This always statement automatically cycles between clock high and clock low in HP (Half Period) time. Makes writing test-benches easier.
always #HP clk = ~clk;

initial begin
    
	$dumpfile("hockey.vcd"); //  * Our waveform is saved under this file.
    $dumpvars(0,hockey_tb); // * Get the variables from the module.
    
    $display("Simulation started.");

    clk = 0; 
    rst = 0;
    BTN_A = 0;
	BTN_B = 0;
	DIR_A = 0;
	DIR_B = 0;
    Y_in_A = 0;
    Y_in_B = 0;
    
	#FP;
	rst=1;
	#FP;
	rst=0;
	
	// Here, you are asked to write your test scenario.



	//My test sceniro is A's victory. Score will be A-B : 3-2. Also between the score 1-1 and 2-1 that round is pretty competetive. 
	
	#FP
	BTN_A = 1;

	#FP
    BTN_A = 0;
	DIR_A = 0 ; //straight shot.
	Y_in_A = 0;
	BTN_A = 1;
	#FP
	BTN_A = 0;
	#(FP * 200);

	// B's turn

	#FP
	DIR_B = 0;
	Y_in_B = 2; //false prediction.
	BTN_B = 1;
	#FP
	BTN_B = 0;
	#(FP * 200);
	
	//SCORE A-B : 1-0
	// B again, because they lost. initial shot.

	#FP
	DIR_B = 1; //upward shot.
	Y_in_B = 1;
	BTN_B = 1;
	#FP
	BTN_B = 0;
	#(FP * 200);
	

	// A's turn

	#FP
	DIR_A = 2; //down
	Y_in_A = 3;
	BTN_A = 1;
	#FP
	BTN_A = 0;
	#(FP * 200);

	// B's turn

	#FP
	DIR_B = 0; //straight
	Y_in_B = 1; 
	BTN_B = 1;
	#FP
	BTN_B = 0;
	#(FP * 200);


		
	// A's turn

	#FP
	DIR_A = 2; //downward
	Y_in_A = 3; // false prediction.
	BTN_A = 1;
	#FP
	BTN_A = 0;
	#(FP * 200);

	// Score A-B : 1-1
	// A AGAIN initial shot


    #FP
	DIR_A = 2; //down
	Y_in_A = 4;
	BTN_A = 1;
	#FP
	BTN_A = 0;
	#(FP * 200);
	
	//B's turn

	#FP
	DIR_B = 0; //straight
	Y_in_B = 0; 
	BTN_B = 1;
	#FP
	BTN_B = 0;
	#(FP * 200);

	//A's turn

	#FP
	DIR_A = 1; //up
	Y_in_A = 0;
	BTN_A = 1;
	#FP
	BTN_A = 0;
	#(FP * 200);

	//B's turn

	#FP
	DIR_B = 2; //down
	Y_in_B = 4; 
	BTN_B = 1;
	#FP
	BTN_B = 0;
	#(FP * 200);
	
	//A's turn

	#FP
	DIR_A = 0; //straight
	Y_in_A = 0;
	BTN_A = 1;
	#FP
	BTN_A = 0;
	#(FP * 200);

	//B's turn

	#FP
	DIR_B = 1; //upward
	Y_in_B = 3; //false prediction
	BTN_B = 1;
	#FP
	BTN_B = 0;
	#(FP * 200);

	//New score A-B : 2-1

	//B's turn again

	#FP
	DIR_B = 1; //upward
	Y_in_B = 2; 
	BTN_B = 1;
	#FP
	BTN_B = 0;
	#(FP * 200);


	//A's turn.

	#FP
	DIR_A = 0; //straight
	Y_in_A = 2;
	BTN_A = 1;
	#FP
	BTN_A = 0;
	#(FP * 200);

	//B's turn.

	#FP
	DIR_B = 2; //downward
	Y_in_B = 2; 
	BTN_B = 1;
	#FP
	BTN_B = 0;
	#(FP * 200);

	//A's turn. 

	#FP
	DIR_A = 1; //up
	Y_in_A = 4; // false prediction.
	BTN_A = 1;
	#FP
	BTN_A = 0;
	#(FP * 200);

	// New score A-B : 2-2

	//A turn's again because they lost this round. 

	#FP
	DIR_A = 0; //straight
	Y_in_A = 3;
	BTN_A = 1;
	#FP
	BTN_A = 0;
	#(FP * 200);

	//B turn's.

	#FP
	DIR_B = 1; //up
	Y_in_B = 4 ; //false prediction.
	BTN_B = 1;
	#FP
	BTN_B = 0;
	#(FP * 200);

	// New score A-B : 3-2
	// A WON THE GAME !!!



	$display("Simulation finished.");
    $finish(); // Finish simulation.
end



endmodule

hockey.vcd
$date
	Sun Jan  7 20:15:42 2024
$end
$version
	Icarus Verilog
$end
$timescale
	1ps
$end
$scope module hockey_tb $end
$var wire 3 ! Y_COORD [2:0] $end
$var wire 3 " X_COORD [2:0] $end
$var wire 7 # SSD5 [6:0] $end
$var wire 7 $ SSD4 [6:0] $end
$var wire 7 % SSD2 [6:0] $end
$var wire 7 & SSD0 [6:0] $end
$var wire 1 ' LD9 $end
$var wire 1 ( LD8 $end
$var wire 1 ) LD7 $end
$var wire 1 * LD6 $end
$var wire 1 + LD5 $end
$var wire 1 , LD15 $end
$var wire 1 - LD0 $end
$var parameter 64 . FP $end
$var parameter 32 / HP $end
$var reg 1 0 BTN_A $end
$var reg 1 1 BTN_B $end
$var reg 2 2 DIR_A [1:0] $end
$var reg 2 3 DIR_B [1:0] $end
$var reg 3 4 Y_in_A [2:0] $end
$var reg 3 5 Y_in_B [2:0] $end
$var reg 1 6 clk $end
$var reg 1 7 rst $end
$scope module dut $end
$var wire 1 0 BTN_A $end
$var wire 1 1 BTN_B $end
$var wire 2 8 DIR_A [1:0] $end
$var wire 2 9 DIR_B [1:0] $end
$var wire 3 : Y_in_A [2:0] $end
$var wire 3 ; Y_in_B [2:0] $end
$var wire 1 6 clk $end
$var wire 1 7 rst $end
$var parameter 4 < DISP $end
$var parameter 4 = END_state $end
$var parameter 4 > GOAL_A $end
$var parameter 4 ? GOAL_B $end
$var parameter 4 @ HIT_A $end
$var parameter 4 A HIT_B $end
$var parameter 4 B IDLE $end
$var parameter 4 C RESP_A $end
$var parameter 4 D RESP_B $end
$var parameter 4 E SEND_A $end
$var parameter 4 F SEND_B $end
$var reg 1 - LD0 $end
$var reg 1 , LD15 $end
$var reg 1 + LD5 $end
$var reg 1 * LD6 $end
$var reg 1 ) LD7 $end
$var reg 1 ( LD8 $end
$var reg 1 ' LD9 $end
$var reg 7 G SSD0 [6:0] $end
$var reg 7 H SSD1 [6:0] $end
$var reg 7 I SSD2 [6:0] $end
$var reg 7 J SSD3 [6:0] $end
$var reg 7 K SSD4 [6:0] $end
$var reg 7 L SSD5 [6:0] $end
$var reg 7 M SSD6 [6:0] $end
$var reg 7 N SSD7 [6:0] $end
$var reg 2 O Score_A [1:0] $end
$var reg 2 P Score_B [1:0] $end
$var reg 4 Q State [3:0] $end
$var reg 2 R Timer [1:0] $end
$var reg 1 S Turn $end
$var reg 3 T X_COORD [2:0] $end
$var reg 3 U Y_COORD [2:0] $end
$var reg 2 V direction_Y [1:0] $end
$upscope $end
$upscope $end
$enddefinitions $end
$comment Show the parameter values. $end
$dumpall
b101 F
b100 E
b111 D
b110 C
b0 B
b11 A
b10 @
b1001 ?
b1000 >
b1010 =
b1 <
b101 /
b1010 .
$end
#0
$dumpvars
bx V
bx U
bx T
xS
bx R
bx Q
bx P
bx O
bx N
bx M
bx L
bx K
bx J
bx I
bx H
bx G
b0 ;
b0 :
b0 9
b0 8
07
06
b0 5
b0 4
b0 3
b0 2
01
00
x-
x,
x+
x*
x)
x(
x'
bx &
bx %
bx $
bx #
bx "
bx !
$end
#5000
16
#10000
0,
0'
0(
0)
0*
0+
0-
b0 &
b0 G
b0 %
b0 I
b0 !
b0 U
b0 "
b0 T
b0 P
b0 O
b0 R
b0 Q
06
17
#15000
16
#20000
06
07
#25000
16
#30000
06
10
#35000
b1 Q
0S
16
#40000
06
10
#45000
b1 R
b1111110 H
16
#50000
06
00
#55000
b10 R
16
#60000
06
#65000
b10 Q
b0 R
16
#70000
06
#75000
b0 H
1,
16
